startling_lib/__init__.py
startling_lib/competence/__init__.py
startling_lib/competence/competence.py
startling_lib/cv/__init__.py
startling_lib/engineering/__init__.py
startling_lib-0.1.2.dist-info/METADATA
startling_lib-0.1.2.dist-info/WHEEL
startling_lib-0.1.2.dist-info/top_level.txt
startling_lib-0.1.2.dist-info/RECORD
