Metadata-Version: 2.4
Name: startling-lib
Version: 0.1.2
Summary: Une bibliothèque minimale faite par startlingadama
Author-email: Adama Coulibaly <startlingadama@email.com>
License: MIT
Project-URL: Homepage, https://github.com/startlingadama/startling-lib.git
Requires-Python: >=3.11
